nasminer/__init__.py
nasminer/common.py
nasminer/crawler.py
nasminer/csv.py
nasminer/sql.py
nasminer/dicom/__init__.py
nasminer/edf/__init__.py
nasminer/ixtrend/__init__.py
nasminer/ixtrend/analyze_csv.py
nasminer/mict/__init__.py
nasminer/syringes/__init__.py
nasminer/syringes/match_syr_lbl.py
nasminer-2022.3.14.dist-info/LICENSE
nasminer-2022.3.14.dist-info/WHEEL
nasminer-2022.3.14.dist-info/METADATA
nasminer-2022.3.14.dist-info/RECORD
