Metadata-Version: 2.1
Name: nasminer
Version: 2022.3.14
Summary: Mine the NAS.
Home-page: https://framagit.org/jaj/nasminer
Author: Jona JOACHIM
Author-email: jona@joachim.cc
Requires-Python: >=3.6
Classifier: License :: OSI Approved :: ISC License (ISCL)
Requires-Dist: numpy>=1.21.4
Requires-Dist: pandas>=1.3.4
Requires-Dist: SQLAlchemy>=1.4.26
Requires-Dist: psycopg2>=2.9.1
Requires-Dist: puremagic>=1.11
Requires-Dist: pydicom>=2.2.2
Requires-Dist: pyEDFlib>=0.1.22
Requires-Dist: python-dateutil>=2.8.2
Requires-Dist: Levenshtein>=0.16.0
Requires-Dist: openpyxl>=3.0.9
